langchainlib/__init__.py
langchainlib/filter_provider.py
langchainlib/plainid_anonymizer.py
langchainlib/plainid_categorizer.py
langchainlib/plainid_client.py
langchainlib/plainid_filter_provider.py
langchainlib/plainid_permissions_provider.py
langchainlib/plainid_retriever.py
langchainlib-0.1.4.dist-info/METADATA
langchainlib-0.1.4.dist-info/WHEEL
langchainlib-0.1.4.dist-info/RECORD
